yutori/__init__.py
yutori/_http.py
yutori/async_client.py
yutori/client.py
yutori/config.py
yutori/exceptions.py
yutori/_async/__init__.py
yutori/_async/browsing.py
yutori/_async/chat.py
yutori/_async/research.py
yutori/_async/scouts.py
yutori/_sync/__init__.py
yutori/_sync/browsing.py
yutori/_sync/chat.py
yutori/_sync/research.py
yutori/_sync/scouts.py
yutori-0.2.0.dist-info/licenses/LICENSE
yutori-0.2.0.dist-info/METADATA
yutori-0.2.0.dist-info/WHEEL
yutori-0.2.0.dist-info/top_level.txt
yutori-0.2.0.dist-info/RECORD
