Metadata-Version: 2.4
Name: yutori
Version: 0.2.0
Summary: Official Python SDK for the Yutori API
Author-email: Yutori <support@yutori.com>
License: Apache License 2.0
Project-URL: Homepage, https://yutori.com
Project-URL: Documentation, https://docs.yutori.com
Project-URL: Repository, https://github.com/yutori-ai/yutori-sdk-python
Project-URL: Issues, https://github.com/yutori-ai/yutori-sdk-python/issues
Keywords: yutori,sdk,api,automation,web-agent,browser,ai
Classifier: Development Status :: 4 - Beta
Classifier: Intended Audience :: Developers
Classifier: License :: OSI Approved :: Apache Software License
Classifier: Operating System :: OS Independent
Classifier: Programming Language :: Python :: 3
Classifier: Programming Language :: Python :: 3.9
Classifier: Programming Language :: Python :: 3.10
Classifier: Programming Language :: Python :: 3.11
Classifier: Programming Language :: Python :: 3.12
Classifier: Programming Language :: Python :: 3.13
Classifier: Typing :: Typed
Requires-Python: >=3.9
License-File: LICENSE
Requires-Dist: httpx<0.28.0,>=0.26.0
Requires-Dist: openai>=1.0.0
Provides-Extra: dev
Requires-Dist: pytest>=7.0; extra == "dev"
Requires-Dist: pytest-asyncio>=0.21; extra == "dev"
Requires-Dist: ruff>=0.1; extra == "dev"
Provides-Extra: examples
Requires-Dist: loguru>=0.7.0; extra == "examples"
Requires-Dist: pillow>=10.0.0; extra == "examples"
Requires-Dist: playwright>=1.40.0; extra == "examples"
Requires-Dist: pydantic>=2.0.0; extra == "examples"
Requires-Dist: tenacity>=9.0.0; extra == "examples"
Dynamic: license-file
